query_data.py
kk_data_query_mcp-0.1.1.dist-info/METADATA
kk_data_query_mcp-0.1.1.dist-info/WHEEL
kk_data_query_mcp-0.1.1.dist-info/entry_points.txt
kk_data_query_mcp-0.1.1.dist-info/top_level.txt
kk_data_query_mcp-0.1.1.dist-info/RECORD
