Metadata-Version: 2.4
Name: kk-data-query-mcp
Version: 0.1.1
Summary: kk todo
Requires-Python: >=3.13
Requires-Dist: httpx>=0.28.1
Requires-Dist: mcp[cli]>=1.7.1
Requires-Dist: pycryptodome>=3.22.0
Requires-Dist: pymysql>=1.1.1
